arithoperaion/__init__.py
arithoperaion/add.py
arithoperaion/subtract.py
arithoperaion/extras/__init__.py
arithoperaion/extras/divide.py
arithoperaion/extras/multiply.py
arithoperaion-0.0.1.dist-info/METADATA
arithoperaion-0.0.1.dist-info/WHEEL
arithoperaion-0.0.1.dist-info/top_level.txt
arithoperaion-0.0.1.dist-info/RECORD
