Metadata-Version: 2.1
Name: arithoperaion
Version: 0.0.1
Summary: My first Python package
Home-page: UNKNOWN
Author: Ramamoorthy
Author-email: <raamamoorthy@gmail.com>
License: UNKNOWN
Keywords: python,first package
Platform: UNKNOWN
Classifier: Development Status :: 3 - Alpha
Classifier: Intended Audience :: Education
Classifier: Programming Language :: Python :: 2
Classifier: Programming Language :: Python :: 3
Classifier: Operating System :: MacOS :: MacOS X
Classifier: Operating System :: Microsoft :: Windows
